rxfoundry/__init__.py
rxfoundry/clients/__init__.py
rxfoundry/clients/swifty_oauth_api/__init__.py
rxfoundry/clients/swifty_oauth_api/api_client.py
rxfoundry/clients/swifty_oauth_api/api_response.py
rxfoundry/clients/swifty_oauth_api/configuration.py
rxfoundry/clients/swifty_oauth_api/exceptions.py
rxfoundry/clients/swifty_oauth_api/py.typed
rxfoundry/clients/swifty_oauth_api/rest.py
rxfoundry/clients/swifty_oauth_api/api/__init__.py
rxfoundry/clients/swifty_oauth_api/api/o_auth_api.py
rxfoundry/clients/swifty_oauth_api/models/__init__.py
rxfoundry/clients/swifty_oauth_api/models/get_token_request.py
rxfoundry/clients/swifty_oauth_api/models/oauth_token_post_request.py
rxfoundry/clients/swifty_oauth_api/models/token_response.py
rxfoundry/clients/swifty_oauth_api/models/user_info_response.py
rxfoundry_clients_swifty_oauth_api-0.1.1018.dist-info/METADATA
rxfoundry_clients_swifty_oauth_api-0.1.1018.dist-info/WHEEL
rxfoundry_clients_swifty_oauth_api-0.1.1018.dist-info/top_level.txt
rxfoundry_clients_swifty_oauth_api-0.1.1018.dist-info/RECORD
