Metadata-Version: 2.4
Name: rxfoundry.clients.swifty-oauth-api
Version: 0.1.1018
Summary: Swifty OAuth API
Home-page: 
Author: RxFoundry Team
Author-email: paul.tindall@rxfoundry.com
Keywords: OpenAPI,OpenAPI-Generator,Swifty OAuth API
Requires-Dist: urllib3<3.0.0,>=2.1.0
Requires-Dist: python-dateutil>=2.8.2
Requires-Dist: pydantic>=2
Requires-Dist: typing-extensions>=4.7.1
Dynamic: author
Dynamic: author-email
Dynamic: description
Dynamic: description-content-type
Dynamic: keywords
Dynamic: requires-dist
Dynamic: summary
